gela/__init__.py
gela-0.1.dist-info/METADATA
gela-0.1.dist-info/WHEEL
gela-0.1.dist-info/top_level.txt
gela-0.1.dist-info/RECORD
