Metadata-Version: 2.1
Name: gela
Version: 0.1
Summary: A Python module that provides a Base class for value management.
Home-page: 
Author: Your Name
Author-email: davitidatunashvili98@gmail.com
License: MIT
Classifier: Programming Language :: Python :: 3
Classifier: License :: OSI Approved :: MIT License
Classifier: Operating System :: OS Independent
Requires-Python: >=3.6
